README.md
setup.py
chem_utils/__init__.py
chem_utils.egg-info/PKG-INFO
chem_utils.egg-info/SOURCES.txt
chem_utils.egg-info/dependency_links.txt
chem_utils.egg-info/requires.txt
chem_utils.egg-info/top_level.txt
chem_utils/chem_handler/__init__.py
chem_utils/chem_handler/atom_handler.py
chem_utils/chem_handler/mol_handler.py
chem_utils/chem_handler/rxn_checker.py
chem_utils/mol_handler/__init__.py
chem_utils/mol_handler/formula_parse.py
chem_utils/mol_handler/mol_3d_gen.py
chem_utils/mol_handler/mol_smiles.py
chem_utils/rxn_handler/__init__.py
chem_utils/rxn_handler/rxn_cleaner.py
chem_utils/rxn_handler/rxn_mapper.py
chem_utils/rxn_handler/rxn_smiles.py
chem_utils/rxn_template/__init__.py
chem_utils/rxn_template/rxn_center_detector.py
chem_utils/rxn_template/rxn_template_extractor.py
chem_utils/chem_handler/__init__.py
chem_utils/chem_handler/atom_handler.py
chem_utils/chem_handler/mol_handler.py
chem_utils/chem_handler/rxn_checker.py
chem_utils/mol_handler/__init__.py
chem_utils/mol_handler/formula_parse.py
chem_utils/mol_handler/mol_3d_gen.py
chem_utils/mol_handler/mol_smiles.py
chem_utils/rxn_handler/__init__.py
chem_utils/rxn_handler/rxn_cleaner.py
chem_utils/rxn_handler/rxn_mapper.py
chem_utils/rxn_handler/rxn_smiles.py
chem_utils/rxn_template/__init__.py
chem_utils/rxn_template/rxn_center_detector.py
chem_utils/rxn_template/rxn_template_extractor.py