Metadata-Version: 2.1
Name: chem-utils
Version: 0.1.2
Summary: reaction database utils
Home-page: https://github.com/zbc0315/chem_utils
Author: zbc
Author-email: zbc@mail.ustc.edu.cn
License: UNKNOWN
Platform: UNKNOWN
Classifier: Programming Language :: Python :: 3
Classifier: License :: OSI Approved :: MIT License
Classifier: Operating System :: OS Independent
Requires-Python: >=3.7
